odoo8_addon_l10n_ar_bank_statement-8.0.1.0.0-py2.7-nspkg.pth
odoo_addons/l10n_ar_bank_statement/account_voucher_view.xml
odoo_addons/l10n_ar_bank_statement/__openerp__.py
odoo_addons/l10n_ar_bank_statement/payment_mode_receipt_view.xml
odoo_addons/l10n_ar_bank_statement/payment_mode_receipt.py
odoo_addons/l10n_ar_bank_statement/account.py
odoo_addons/l10n_ar_bank_statement/account_voucher.py
odoo_addons/l10n_ar_bank_statement/__init__.py
odoo_addons/l10n_ar_bank_statement/bank_import_statement_lines_view.xml
odoo_addons/l10n_ar_bank_statement/bank_statement.py
odoo_addons/l10n_ar_bank_statement/i18n/es_AR.po
odoo_addons/l10n_ar_bank_statement/i18n/es_AR.mo
odoo_addons/l10n_ar_bank_statement/wizard/project_import_wizard.py
odoo_addons/l10n_ar_bank_statement/wizard/__init__.py
odoo_addons/l10n_ar_bank_statement/wizard/account_import_bank_statement_view.xml
odoo_addons/l10n_ar_bank_statement/wizard/account_import_bank_statement.py
odoo_addons/l10n_ar_bank_statement/wizard/project_import_wizard_view.xml
odoo_addons/l10n_ar_bank_statement/wizard/xml/0181 - Overhaul K2110 Sierra Chata - 130802 - cgil.xml
odoo8_addon_l10n_ar_bank_statement-8.0.1.0.0.dist-info/top_level.txt
odoo8_addon_l10n_ar_bank_statement-8.0.1.0.0.dist-info/WHEEL
odoo8_addon_l10n_ar_bank_statement-8.0.1.0.0.dist-info/RECORD
odoo8_addon_l10n_ar_bank_statement-8.0.1.0.0.dist-info/metadata.json
odoo8_addon_l10n_ar_bank_statement-8.0.1.0.0.dist-info/DESCRIPTION.rst
odoo8_addon_l10n_ar_bank_statement-8.0.1.0.0.dist-info/METADATA
odoo8_addon_l10n_ar_bank_statement-8.0.1.0.0.dist-info/namespace_packages.txt
